nplusone/__init__.py
nplusone/core/__init__.py
nplusone/core/exceptions.py
nplusone/core/listeners.py
nplusone/core/notifiers.py
nplusone/core/profiler.py
nplusone/core/signals.py
nplusone/core/stack.py
nplusone/ext/__init__.py
nplusone/ext/flask_sqlalchemy.py
nplusone/ext/peewee.py
nplusone/ext/sqlalchemy.py
nplusone/ext/wsgi.py
nplusone/ext/django/__init__.py
nplusone/ext/django/middleware.py
nplusone/ext/django/patch.py
nplusone_TrialSpark-1.0.3.dist-info/AUTHORS.rst
nplusone_TrialSpark-1.0.3.dist-info/LICENSE
nplusone_TrialSpark-1.0.3.dist-info/METADATA
nplusone_TrialSpark-1.0.3.dist-info/WHEEL
nplusone_TrialSpark-1.0.3.dist-info/top_level.txt
nplusone_TrialSpark-1.0.3.dist-info/RECORD
