Metadata-Version: 2.1
Name: nplusone-TrialSpark
Version: 1.0.3
Summary: Detecting the n+1 queries problem in Python
Home-page: https://github.com/trialspark/nplusone
Author: Joshua Carp
Author-email: jm.carp@gmail.com
License: MIT
Keywords: nplusone
Platform: UNKNOWN
Classifier: Development Status :: 2 - Pre-Alpha
Classifier: Intended Audience :: Developers
Classifier: License :: OSI Approved :: MIT License
Classifier: Natural Language :: English
Classifier: Programming Language :: Python :: 2
Classifier: Programming Language :: Python :: 2.7
Classifier: Programming Language :: Python :: 3
Classifier: Programming Language :: Python :: 3.3
Classifier: Programming Language :: Python :: 3.4
Classifier: Programming Language :: Python :: 3.5
Classifier: Programming Language :: Python :: 3.6
Classifier: Programming Language :: Python :: 3.7
Classifier: Programming Language :: Python :: 3.8
Requires-Dist: six (>=1.9.0)
Requires-Dist: blinker (>=1.3)
Requires-Dist: structlog (>=18.2.0)
